LICENSE.iitm
LICENSE.incore
MANIFEST.in
README.rst
setup.cfg
setup.py
csrbox/__init__.py
csrbox/attributes.yaml
csrbox/constants.py
csrbox/csr_gen.py
csrbox/csrgrp_check.py
csrbox/errors.py
csrbox/log.py
csrbox/main.py
csrbox/requirements.txt
csrbox/utils.py
csrbox.egg-info/PKG-INFO
csrbox.egg-info/SOURCES.txt
csrbox.egg-info/dependency_links.txt
csrbox.egg-info/entry_points.txt
csrbox.egg-info/not-zip-safe
csrbox.egg-info/requires.txt
csrbox.egg-info/top_level.txt